fast_bi_dbt_runner/__init__.py
fast_bi_dbt_runner/airbyte_task_group_builder.py
fast_bi_dbt_runner/dbt_manifest_parser_api_operator.py
fast_bi_dbt_runner/dbt_manifest_parser_bash_operator.py
fast_bi_dbt_runner/dbt_manifest_parser_gke_operator.py
fast_bi_dbt_runner/dbt_manifest_parser_k8s_operator.py
fast_bi_dbt_runner/bash_operator/__init__.py
fast_bi_dbt_runner/bash_operator/dbt_hook.py
fast_bi_dbt_runner/bash_operator/dbt_operator.py
fast_bi_dbt_runner-2025.1.3.1.dist-info/METADATA
fast_bi_dbt_runner-2025.1.3.1.dist-info/WHEEL
fast_bi_dbt_runner-2025.1.3.1.dist-info/top_level.txt
fast_bi_dbt_runner-2025.1.3.1.dist-info/RECORD
